pyMILP/__init__.py
pyMILP/constraint.py
pyMILP/expression.py
pyMILP/problem.py
pyMILP/tutorial.py
pyMILP/variable.py
pyMILP-1.0.0.dist-info/LICENSE.txt
pyMILP-1.0.0.dist-info/METADATA
pyMILP-1.0.0.dist-info/WHEEL
pyMILP-1.0.0.dist-info/top_level.txt
pyMILP-1.0.0.dist-info/RECORD
